pykrx_openapi/__init__.py
pykrx_openapi/_version.py
pykrx_openapi/client.py
pykrx_openapi/constants.py
pykrx_openapi/converters.py
pykrx_openapi/exceptions.py
pykrx_openapi/logger.py
pykrx_openapi/rate_limiter.py
pykrx_openapi-0.1.1.dist-info/METADATA
pykrx_openapi-0.1.1.dist-info/WHEEL
pykrx_openapi-0.1.1.dist-info/licenses/LICENSE
pykrx_openapi-0.1.1.dist-info/RECORD
