Metadata-Version: 2.4
Name: pykrx-openapi
Version: 0.1.1
Summary: Python wrapper for KRX (Korea Exchange) OpenAPI
Project-URL: Homepage, https://github.com/raccoonyy/pykrx-openapi
Project-URL: Documentation, https://github.com/raccoonyy/pykrx-openapi#readme
Project-URL: Repository, https://github.com/raccoonyy/pykrx-openapi
Project-URL: Issues, https://github.com/raccoonyy/pykrx-openapi/issues
Author: Alan Kim
License: MIT
License-File: LICENSE
Keywords: api,finance,korea exchange,krx,stock
Classifier: Development Status :: 3 - Alpha
Classifier: Intended Audience :: Developers
Classifier: Intended Audience :: Financial and Insurance Industry
Classifier: License :: OSI Approved :: MIT License
Classifier: Programming Language :: Python :: 3.8
Classifier: Programming Language :: Python :: 3.9
Classifier: Programming Language :: Python :: 3.10
Classifier: Programming Language :: Python :: 3.11
Classifier: Programming Language :: Python :: 3.12
Classifier: Programming Language :: Python :: 3.13
Classifier: Topic :: Office/Business :: Financial :: Investment
Requires-Python: >=3.8
Requires-Dist: requests>=2.32.0
